flask_hmac_auth_client/__init__.py
flask_hmac_auth_client_m4l1c3-1.0.0.dist-info/LICENSE
flask_hmac_auth_client_m4l1c3-1.0.0.dist-info/METADATA
flask_hmac_auth_client_m4l1c3-1.0.0.dist-info/WHEEL
flask_hmac_auth_client_m4l1c3-1.0.0.dist-info/top_level.txt
flask_hmac_auth_client_m4l1c3-1.0.0.dist-info/RECORD
